{
  "users": [
    {
      "cnpj": "94.583.479/0001-28",
      "email": "condominiobelojardim.com.br",
      "senha": "condo",
      "id": "1"
    },
    {
      "cnpj": "94.583.479/0001-28",
      "email": "condominiobelojardim.com.br",
      "password": "condo",
      "id": "2"
    },
    {
      "cnpj": "94.583.479/0001-28",
      "email": "condominiobelojardim.com.br",
      "password": "condo",
      "id": "3"
    },
    {
      "cnpj": "94.583.479/0001-28",
      "email": "condominiobelojardim.com.br",
      "password": "condo",
      "id": "4"
    },
    {
      "cnpj": "94.583.479/0001-28",
      "email": "condominiobelojardim.com.br",
      "password": "condo",
      "id": "5"
    }
  ],
  "condominio": [
    {
      "cnpj": "94.583.479/0001-28",
      "razaoSocial": "Condomínio Exemplo",
      "email": "condominio@example.com",
      "senha": "senha123",
      "id": "1"
    },
    {
      "cnpj": "94.583.479/0001-28",
      "razaoSocial": "Condomínio Exemplo",
      "email": "condominio@example.com",
      "senha": "senha123",
      "id": "2"
    }
  ],
  "espaco": [
    {
      "nomeEspaco": "Academia",
      "capacidade": 50,
      "tempoReserva": "2 horas",
      "instrucoes": "Beber bastante agua",
      "CONDOMINIO_ID": 1,
      "id": "1"
    },
    {
      "nomeEspaco": "Churrasqueira",
      "capacidade": 100,
      "tempo_Reserva": "1 hora",
      "instrucoes": "Usar equipamentos com cuidado",
      "CONDOMINIO_ID": 1,
      "id": "2"
    },
    {
      "id": "835c"
    },
    {
      "id": "f3f1"
    },
    {
      "id": "fc41"
    },
    {
      "id": "7338"
    },
    {
      "id": "8433"
    },
    {
      "id": "d823"
    },
    {
      "id": "b06f"
    },
    {
      "id": "c070"
    },
    {
      "id": "51ed"
    },
    {
      "id": "8ec6"
    },
    {
      "id": "f8b0"
    },
    {
      "id": "9db5"
    },
    {
      "id": "fbe1"
    },
    {
      "id": "f255"
    },
    {
      "id": "9620"
    },
    {
      "id": "e2a7"
    },
    {
      "id": "cf3a"
    },
    {
      "id": "09cb"
    },
    {
      "id": "7cbe"
    },
    {
      "id": "bd07"
    },
    {
      "id": "8c7a"
    },
    {
      "id": "ed9d"
    },
    {
      "id": "c3a1"
    },
    {
      "id": "ee58"
    },
    {
      "id": "4496"
    },
    {
      "id": "5305"
    },
    {
      "id": "a51d"
    },
    {
      "id": "5570"
    },
    {
      "id": "748b"
    },
    {
      "id": "d112"
    },
    {
      "id": "7847"
    },
    {
      "id": "e2a7"
    },
    {
      "id": "de71"
    },
    {
      "id": "e7c0"
    },
    {
      "id": "5abb"
    },
    {
      "id": "8372"
    },
    {
      "id": "1d5e"
    },
    {
      "id": "135b"
    },
    {
      "id": "5dfb"
    },
    {
      "id": "8719"
    },
    {
      "id": "a28f"
    },
    {
      "id": "ddf7"
    },
    {
      "id": "732d"
    },
    {
      "id": "998d"
    }
  ],
  "bloco": [
    {
      "id": "1",
      "apto_id": [
        1
      ]
    }
  ],
  "apartamento": [
    {
      "nomeTitular": "Alvaro Dias",
      "cpfTitular": "70043856632",
      "dataNascimento": "05/06/1999",
      "idade": "24",
      "genero": "Masculino",
      "bloco": "05",
      "numeroApartamento": "128",
      "Condominio_ID": "",
      "bloco_id": "",
      "id": "1"
    },
    {
      "nomeTitular": "Mariane Oliveira",
      "cpfTitular": "02567812345",
      "dataNascimento": "03/02/1992",
      "idade": "26",
      "genero": "Feminino",
      "bloco": "02",
      "numeroApartamento": "246",
      "Condominio_ID": "",
      "bloco_id": "",
      "id": "2"
    },
    {
      "id": "ab1b"
    },
    {
      "id": "deef"
    },
    {
      "id": "011e"
    },
    {
      "id": "e75b"
    },
    {
      "id": "c8ab"
    },
    {
      "id": "1cf1"
    },
    {
      "id": "37d8"
    },
    {
      "id": "b109"
    },
    {
      "id": "7a72"
    },
    {
      "id": "f9f5"
    },
    {
      "id": "509b"
    },
    {
      "id": "9925"
    },
    {
      "id": "cae6"
    },
    {
      "id": "2635"
    },
    {
      "id": "fb7a"
    },
    {
      "id": "1d98"
    },
    {
      "id": "8000"
    },
    {
      "id": "825a"
    },
    {
      "id": "e12e"
    },
    {
      "id": "11e0"
    },
    {
      "id": "879d"
    },
    {
      "id": "2adc"
    },
    {
      "id": "93b9"
    },
    {
      "id": "89e9"
    },
    {
      "id": "4e70"
    },
    {
      "id": "519b"
    },
    {
      "id": "4d3f"
    },
    {
      "id": "4379"
    },
    {
      "id": "a962"
    },
    {
      "id": "0d19"
    },
    {
      "id": "ad5b"
    },
    {
      "id": "8e69"
    },
    {
      "id": "2e4c"
    },
    {
      "id": "264c"
    },
    {
      "id": "6e57"
    },
    {
      "id": "b8fc"
    },
    {
      "id": "ea6c"
    },
    {
      "id": "6ea3"
    },
    {
      "id": "135a"
    },
    {
      "id": "a4ff"
    },
    {
      "id": "33b2"
    },
    {
      "id": "8e9f"
    },
    {
      "id": "598f"
    },
    {
      "id": "c48c"
    },
    {
      "id": "7390"
    },
    {
      "id": "9edf"
    }
  ],
  "titular": [
    {
      "nomeTitular": "Amanda Silva",
      "cpfTitular": "12345678900",
      "Data_Nasc": "01/05/2000",
      "idade": 31,
      "bloco_id": 1,
      "apto_id": 1,
      "id": "1"
    },
    {
      "nomeTitular": "Mariane Oliveira",
      "cpfTitular": "12345678900",
      "Data_Nasc": "01/05/2000",
      "idade": 31,
      "bloco_id": 1,
      "apto_id": 1,
      "id": "2"
    },
    {
      "nomeTitular": "Mariane Oliveira",
      "cpfTitular": "12345678900",
      "Data_Nasc": "01/05/2000",
      "idade": 31,
      "bloco_id": 1,
      "apto_id": 1,
      "id": "3"
    }
  ],
  "dependente": [
    {
      "nomeDependente": "Pedro Henrique",
      "cpfDependente": 23456789012,
      "data_Nasc": "05/08/1000",
      "id": "3"
    },
    {
      "id": "8107",
      "nomeDependente": "Evellyn Andrade",
      "cpfDependente": "14942495610",
      "dataNascimento": "09/02/2005",
      "condomino_Titular_Id": 1,
      "idade": "19"
    }
  ]
}